{
  "openapi": "3.1.0",
  "info": {
    "description": "Collaborative Lifecycle REST Services",
    "version": "1.2.4",
    "title": "Collaborative Lifecycle Web Services",
    "x-ds-service": [
      "3DSpace"
    ],
    "summary": "Collaborative Lifecycle services for managing the objects lifecycle (from creation to deletion) and collaboration (manage concurrent access to objects)",
    "x-ds-copyright": "Copyright Dassault Systemes 2024"
  },
  "security": [
    {
      "BasicAuth": []
    }
  ],
  "servers": [
    {
      "url": "{3DSpace}/resources/v1/modeler/dslc",
      "variables": {
        "3DSpace": {
          "default": "https://3DEXPERIENCE_3DSpace"
        }
      }
    },
    {
      "url": "{APIGateway}/api/dslc/v1",
      "description": "Cloud API Gateway",
      "variables": {
        "APIGateway": {
          "default": "https://my3DEXPERIENCE-APIGateway"
        }
      }
    }
  ],
  "paths": {
    "/maturity/getNextStates": {
      "post": {
        "summary": "Get next maturity states",
        "description": "Gets the next possible maturity states for a list of objects.",
        "operationId": "getNextStates",
        "tags": [
          "Maturity"
        ],
        "parameters": [
          {
            "name": "SecurityContext",
            "in": "header",
            "description": "Security context the logged in user is using like ctx::RoleValue.OrganizationValue.CollaborativeSpaceValue",
            "required": true,
            "schema": {
              "type": "string"
            }
          },
          {
            "name": "ENO_CSRF_TOKEN",
            "in": "header",
            "description": "CSRF token could be obtained from dedicated web service /resources/v1/application/CSRF/",
            "required": true,
            "schema": {
              "type": "string"
            }
          }
        ],
        "requestBody": {
          "content": {
            "application/json": {
              "schema": {
                "$ref": "#/components/schemas/idListInputRef"
              }
            }
          }
        },
        "responses": {
          "200": {
            "description": "Operation completed successfully.",
            "content": {
              "application/json": {
                "schema": {
                  "$ref": "#/components/schemas/getNextStatesOutput"
                }
              }
            }
          },
          "400": {
            "description": "Input is incorrect",
            "content": {
              "application/json": {
                "schema": {
                  "$ref": "#/components/schemas/ErrorOutputLCERROR400001"
                }
              }
            }
          },
          "401": {
            "description": "User is not authorized to access this service",
            "content": {
              "application/json": {
                "schema": {
                  "$ref": "#/components/schemas/ErrorOutputLCERROR401000"
                }
              }
            }
          },
          "403": {
            "description": "CSRF Token Not Validated",
            "content": {
              "application/json": {
                "schema": {
                  "$ref": "#/components/schemas/ErrorOutputLCERROR403000"
                }
              }
            }
          },
          "404": {
            "description": "Not Found",
            "content": {
              "application/json": {
                "schema": {
                  "$ref": "#/components/schemas/ErrorOutputLCERROR404000"
                }
              }
            }
          },
          "500": {
            "description": "Issue occured during request processing.",
            "content": {
              "application/json": {
                "schema": {
                  "$ref": "#/components/schemas/ErrorOutput500"
                }
              }
            }
          }
        }
      }
    },
    "/maturity/changeState": {
      "post": {
        "summary": "Change maturity states",
        "description": "Change maturity state for a list of objects.  You can change maturity to a state only along a single valid transition on the Maturity graph - to find the list of valid next states, use the web service getNextStates.",
        "operationId": "changeState",
        "tags": [
          "Maturity"
        ],
        "parameters": [
          {
            "name": "SecurityContext",
            "in": "header",
            "description": "Security context the logged in user is using like ctx::RoleValue.OrganizationValue.CollaborativeSpaceValue",
            "required": true,
            "schema": {
              "type": "string"
            }
          },
          {
            "name": "ENO_CSRF_TOKEN",
            "in": "header",
            "description": "CSRF token could be obtained from dedicated web service /resources/v1/application/CSRF/",
            "required": true,
            "schema": {
              "type": "string"
            }
          }
        ],
        "requestBody": {
          "content": {
            "application/json": {
              "schema": {
                "$ref": "#/components/schemas/changeStateListInput"
              }
            }
          }
        },
        "responses": {
          "200": {
            "description": "Operation completed successfully.",
            "content": {
              "application/json": {
                "schema": {
                  "$ref": "#/components/schemas/changeStateOutput"
                }
              }
            }
          },
          "400": {
            "description": "Input is incorrect",
            "content": {
              "application/json": {
                "schema": {
                  "$ref": "#/components/schemas/ErrorOutputLCERROR400001"
                }
              }
            }
          },
          "401": {
            "description": "User is not authorized to access this service",
            "content": {
              "application/json": {
                "schema": {
                  "$ref": "#/components/schemas/ErrorOutputLCERROR401000"
                }
              }
            }
          },
          "403": {
            "description": "CSRF Token Not Validated",
            "content": {
              "application/json": {
                "schema": {
                  "$ref": "#/components/schemas/ErrorOutputLCERROR403000"
                }
              }
            }
          },
          "404": {
            "description": "Not Found",
            "content": {
              "application/json": {
                "schema": {
                  "$ref": "#/components/schemas/ErrorOutputLCERROR404000"
                }
              }
            }
          },
          "500": {
            "description": "Issue occured during request processing.",
            "content": {
              "application/json": {
                "schema": {
                  "$ref": "#/components/schemas/ErrorOutput500"
                }
              }
            }
          }
        }
      }
    },
    "/reservation/reserve": {
      "post": {
        "summary": "Reserve objects",
        "description": "Reserve a list of objects by the current user.",
        "operationId": "reserve",
        "tags": [
          "Reservation"
        ],
        "parameters": [
          {
            "name": "SecurityContext",
            "in": "header",
            "description": "Security context the logged in user is using like ctx::RoleValue.OrganizationValue.CollaborativeSpaceValue",
            "required": true,
            "schema": {
              "type": "string"
            }
          },
          {
            "name": "ENO_CSRF_TOKEN",
            "in": "header",
            "description": "CSRF token could be obtained from dedicated web service /resources/v1/application/CSRF/",
            "required": true,
            "schema": {
              "type": "string"
            }
          }
        ],
        "requestBody": {
          "content": {
            "application/json": {
              "schema": {
                "$ref": "#/components/schemas/idListInputRef"
              }
            }
          }
        },
        "responses": {
          "200": {
            "description": "Operation completed successfully.",
            "content": {
              "application/json": {
                "schema": {
                  "$ref": "#/components/schemas/reservationOutput"
                }
              }
            }
          },
          "400": {
            "description": "Input is incorrect",
            "content": {
              "application/json": {
                "schema": {
                  "$ref": "#/components/schemas/ErrorOutputLCERROR400001"
                }
              }
            }
          },
          "401": {
            "description": "User is not authorized to access this service",
            "content": {
              "application/json": {
                "schema": {
                  "$ref": "#/components/schemas/ErrorOutputLCERROR401000"
                }
              }
            }
          },
          "403": {
            "description": "CSRF Token Not Validated",
            "content": {
              "application/json": {
                "schema": {
                  "$ref": "#/components/schemas/ErrorOutputLCERROR403000"
                }
              }
            }
          },
          "404": {
            "description": "Not Found",
            "content": {
              "application/json": {
                "schema": {
                  "$ref": "#/components/schemas/ErrorOutputLCERROR404000"
                }
              }
            }
          },
          "500": {
            "description": "Issue occured during request processing.",
            "content": {
              "application/json": {
                "schema": {
                  "$ref": "#/components/schemas/ErrorOutput500"
                }
              }
            }
          }
        }
      }
    },
    "/reservation/unreserve": {
      "post": {
        "summary": "Uneserve objects",
        "description": "Uneserve a list of objects by the current user.",
        "operationId": "unreserve",
        "tags": [
          "Reservation"
        ],
        "parameters": [
          {
            "name": "SecurityContext",
            "in": "header",
            "description": "Security context the logged in user is using like ctx::RoleValue.OrganizationValue.CollaborativeSpaceValue",
            "required": true,
            "schema": {
              "type": "string"
            }
          },
          {
            "name": "ENO_CSRF_TOKEN",
            "in": "header",
            "description": "CSRF token could be obtained from dedicated web service /resources/v1/application/CSRF/",
            "required": true,
            "schema": {
              "type": "string"
            }
          }
        ],
        "requestBody": {
          "content": {
            "application/json": {
              "schema": {
                "$ref": "#/components/schemas/idListInputRef"
              }
            }
          }
        },
        "responses": {
          "200": {
            "description": "Operation completed successfully.",
            "content": {
              "application/json": {
                "schema": {
                  "$ref": "#/components/schemas/reservationOutput"
                }
              }
            }
          },
          "400": {
            "description": "Input is incorrect",
            "content": {
              "application/json": {
                "schema": {
                  "$ref": "#/components/schemas/ErrorOutputLCERROR400001"
                }
              }
            }
          },
          "401": {
            "description": "User is not authorized to access this service",
            "content": {
              "application/json": {
                "schema": {
                  "$ref": "#/components/schemas/ErrorOutputLCERROR401000"
                }
              }
            }
          },
          "403": {
            "description": "CSRF Token Not Validated",
            "content": {
              "application/json": {
                "schema": {
                  "$ref": "#/components/schemas/ErrorOutputLCERROR403000"
                }
              }
            }
          },
          "404": {
            "description": "Not Found",
            "content": {
              "application/json": {
                "schema": {
                  "$ref": "#/components/schemas/ErrorOutputLCERROR404000"
                }
              }
            }
          },
          "500": {
            "description": "Issue occured during request processing.",
            "content": {
              "application/json": {
                "schema": {
                  "$ref": "#/components/schemas/ErrorOutput500"
                }
              }
            }
          }
        }
      }
    },
    "/sharing/getSharing": {
      "post": {
        "summary": "Get sharing profiles",
        "description": "Get sharing profiles of a list of objects",
        "operationId": "getSharing",
        "tags": [
          "Sharing"
        ],
        "parameters": [
          {
            "name": "SecurityContext",
            "in": "header",
            "description": "Security context the logged in user is using like ctx::RoleValue.OrganizationValue.CollaborativeSpaceValue",
            "required": true,
            "schema": {
              "type": "string"
            }
          },
          {
            "name": "ENO_CSRF_TOKEN",
            "in": "header",
            "description": "CSRF token could be obtained from dedicated web service /resources/v1/application/CSRF/",
            "required": true,
            "schema": {
              "type": "string"
            }
          },
          {
            "name": "Accept",
            "in": "header",
            "description": "application/json",
            "required": true,
            "schema": {
              "type": "string"
            }
          },
          {
            "name": "Content-Type",
            "in": "header",
            "description": "application/json",
            "required": true,
            "schema": {
              "type": "string"
            }
          }
        ],
        "requestBody": {
          "content": {
            "application/json": {
              "schema": {
                "$ref": "#/components/schemas/getSharingInput"
              }
            }
          }
        },
        "responses": {
          "200": {
            "description": "Operation completed successfully.",
            "content": {
              "application/json": {
                "schema": {
                  "$ref": "#/components/schemas/getSharingOutput"
                }
              }
            }
          },
          "400": {
            "description": "Input is incorrect",
            "content": {
              "application/json": {
                "schema": {
                  "$ref": "#/components/schemas/ErrorOutputLCERROR400001"
                }
              }
            }
          },
          "401": {
            "description": "User is not authorized to access this service",
            "content": {
              "application/json": {
                "schema": {
                  "$ref": "#/components/schemas/ErrorOutputLCERROR401000"
                }
              }
            }
          },
          "403": {
            "description": "CSRF Token Not Validated",
            "content": {
              "application/json": {
                "schema": {
                  "$ref": "#/components/schemas/ErrorOutputLCERROR403000"
                }
              }
            }
          },
          "404": {
            "description": "Not Found",
            "content": {
              "application/json": {
                "schema": {
                  "$ref": "#/components/schemas/ErrorOutputLCERROR404000"
                }
              }
            }
          },
          "500": {
            "description": "Issue occured during request processing.",
            "content": {
              "application/json": {
                "schema": {
                  "$ref": "#/components/schemas/ErrorOutput500"
                }
              }
            }
          }
        }
      }
    },
    "/sharing/setSharing": {
      "post": {
        "summary": "Share objects",
        "description": "Share a list of objects with a list of users. Operation is limited to 100 objects at a time.",
        "operationId": "setSharing",
        "tags": [
          "Sharing"
        ],
        "parameters": [
          {
            "name": "SecurityContext",
            "in": "header",
            "description": "Security context the logged in user is using like ctx::RoleValue.OrganizationValue.CollaborativeSpaceValue",
            "required": true,
            "schema": {
              "type": "string"
            }
          },
          {
            "name": "ENO_CSRF_TOKEN",
            "in": "header",
            "description": "CSRF token could be obtained from dedicated web service /resources/v1/application/CSRF/",
            "required": true,
            "schema": {
              "type": "string"
            }
          },
          {
            "name": "Accept",
            "in": "header",
            "description": "application/json",
            "required": true,
            "schema": {
              "type": "string"
            }
          },
          {
            "name": "Content-Type",
            "in": "header",
            "description": "application/json",
            "required": true,
            "schema": {
              "type": "string"
            }
          }
        ],
        "requestBody": {
          "content": {
            "application/json": {
              "schema": {
                "$ref": "#/components/schemas/setSharingInput"
              }
            }
          }
        },
        "responses": {
          "200": {
            "description": "Operation completed successfully.",
            "content": {
              "application/json": {
                "schema": {
                  "$ref": "#/components/schemas/setSharingOutput"
                }
              }
            }
          },
          "400": {
            "description": "Input is incorrect",
            "content": {
              "application/json": {
                "schema": {
                  "$ref": "#/components/schemas/ErrorOutputLCERROR400001"
                }
              }
            }
          },
          "401": {
            "description": "User is not authorized to access this service",
            "content": {
              "application/json": {
                "schema": {
                  "$ref": "#/components/schemas/ErrorOutputLCERROR401000"
                }
              }
            }
          },
          "403": {
            "description": "CSRF Token Not Validated",
            "content": {
              "application/json": {
                "schema": {
                  "$ref": "#/components/schemas/ErrorOutputLCERROR403000"
                }
              }
            }
          },
          "404": {
            "description": "Not Found",
            "content": {
              "application/json": {
                "schema": {
                  "$ref": "#/components/schemas/ErrorOutputLCERROR404000"
                }
              }
            }
          },
          "500": {
            "description": "Issue occured during request processing.",
            "content": {
              "application/json": {
                "schema": {
                  "$ref": "#/components/schemas/ErrorOutput500"
                }
              }
            }
          }
        }
      }
    },
    "/ownership/transfer": {
      "post": {
        "summary": "Transfer ownership",
        "description": "Transfer the ownership for a list of objects. Operation is limited to 1000 objects at a time.",
        "operationId": "transfer",
        "tags": [
          "Ownership"
        ],
        "parameters": [
          {
            "name": "SecurityContext",
            "in": "header",
            "description": "Security context the logged in user is using like ctx::RoleValue.OrganizationValue.CollaborativeSpaceValue",
            "required": true,
            "schema": {
              "type": "string"
            }
          },
          {
            "name": "ENO_CSRF_TOKEN",
            "in": "header",
            "description": "CSRF token could be obtained from dedicated web service /resources/v1/application/CSRF/",
            "required": true,
            "schema": {
              "type": "string"
            }
          },
          {
            "name": "Accept",
            "in": "header",
            "description": "application/json",
            "required": true,
            "schema": {
              "type": "string"
            }
          },
          {
            "name": "content-type",
            "in": "header",
            "description": "application/json",
            "required": true,
            "schema": {
              "type": "string"
            }
          }
        ],
        "requestBody": {
          "content": {
            "application/json": {
              "schema": {
                "$ref": "#/components/schemas/transferListInput"
              }
            }
          }
        },
        "responses": {
          "200": {
            "description": "Operation completed successfully.",
            "content": {
              "application/json": {
                "schema": {
                  "$ref": "#/components/schemas/transferOutput"
                }
              }
            }
          },
          "207": {
            "description": "Operation Partially succeeded.",
            "content": {
              "application/json": {
                "schema": {
                  "$ref": "#/components/schemas/transferOutputPartialSuccess"
                }
              }
            }
          },
          "400": {
            "description": "Input is incorrect",
            "content": {
              "application/json": {
                "schema": {
                  "$ref": "#/components/schemas/ErrorOutput400"
                }
              }
            }
          },
          "401": {
            "description": "User is not authorized to access this service",
            "content": {
              "application/json": {
                "schema": {
                  "$ref": "#/components/schemas/ErrorOutput401"
                }
              }
            }
          },
          "404": {
            "description": "Not Found",
            "content": {
              "application/json": {
                "schema": {
                  "$ref": "#/components/schemas/ErrorOutputLCERROR404000"
                }
              }
            }
          },
          "500": {
            "description": "Issue occured during request processing.",
            "content": {
              "application/json": {
                "schema": {
                  "$ref": "#/components/schemas/ErrorOutput500"
                }
              }
            }
          }
        }
      }
    },
    "/duplicate": {
      "post": {
        "summary": "Duplicate objects",
        "description": "Duplicate a list of objects. The request will be rejected if the total number of objects exceeds 100.",
        "operationId": "duplicate",
        "tags": [
          "Duplicate"
        ],
        "parameters": [
          {
            "name": "SecurityContext",
            "in": "header",
            "description": "Security context the logged in user is using like ctx::RoleValue.OrganizationValue.CollaborativeSpaceValue",
            "required": true,
            "schema": {
              "type": "string"
            }
          },
          {
            "name": "ENO_CSRF_TOKEN",
            "in": "header",
            "description": "CSRF token could be obtained from dedicated web service /resources/v1/application/CSRF/",
            "required": true,
            "schema": {
              "type": "string"
            }
          }
        ],
        "requestBody": {
          "content": {
            "application/json": {
              "schema": {
                "$ref": "#/components/schemas/duplicateidListInput"
              }
            }
          }
        },
        "responses": {
          "200": {
            "description": "Operation completed successfully. Note that the identifier, type, source, and relativePath properties will only be present if they were optionally passed in the request body.",
            "content": {
              "application/json": {
                "schema": {
                  "$ref": "#/components/schemas/duplicateOutput"
                }
              }
            }
          },
          "400": {
            "description": "Input is incorrect",
            "content": {
              "application/json": {
                "schema": {
                  "$ref": "#/components/schemas/ErrorOutputLCERROR400001"
                }
              }
            }
          },
          "401": {
            "description": "User is not authorized to access this service",
            "content": {
              "application/json": {
                "schema": {
                  "$ref": "#/components/schemas/ErrorOutputLCERROR401000"
                }
              }
            }
          },
          "403": {
            "description": "CSRF Token Not Validated",
            "content": {
              "application/json": {
                "schema": {
                  "$ref": "#/components/schemas/ErrorOutputLCERROR403000"
                }
              }
            }
          },
          "404": {
            "description": "Not Found",
            "content": {
              "application/json": {
                "schema": {
                  "$ref": "#/components/schemas/ErrorOutputLCERROR404000"
                }
              }
            }
          },
          "500": {
            "description": "Issue occured during request processing.",
            "content": {
              "application/json": {
                "schema": {
                  "$ref": "#/components/schemas/ErrorOutputDupLCERROR500002"
                }
              }
            }
          }
        }
      }
    },
    "/version/create": {
      "post": {
        "summary": "Version objects",
        "description": "Create new versions for a list of objects. <br/> 1. Versions to create are revisions :  'edgeType' keyword is missing or set to 'Revision' (default value). 'affix' keyword is optional (not used if added). <br/> 2. Versions to create are branches : 'edgeType' keyword is set to 'Branch'. 'affix' keyword is optional (used if added). <br/> The request will be rejected if the total number of objects (after completion excluding relationship) exceeds 100.",
        "operationId": "version",
        "tags": [
          "Versioning"
        ],
        "parameters": [
          {
            "name": "SecurityContext",
            "in": "header",
            "description": "Security context the logged in user is using like ctx::RoleValue.OrganizationValue.CollaborativeSpaceValue",
            "required": true,
            "schema": {
              "type": "string"
            }
          },
          {
            "name": "ENO_CSRF_TOKEN",
            "in": "header",
            "description": "CSRF token could be obtained from dedicated web service /resources/v1/application/CSRF/",
            "required": true,
            "schema": {
              "type": "string"
            }
          },
          {
            "name": "$include",
            "in": "query",
            "description": "option to include more information in the result, limited to Revision mode ! Choose $include=instances to add an instances array that displays created instances under each object",
            "required": false,
            "schema": {
              "type": "string",
              "enum": [
                "instances"
              ]
            }
          }
        ],
        "requestBody": {
          "content": {
            "application/json": {
              "schema": {
                "$ref": "#/components/schemas/idListInputObjectReferenceBranch"
              }
            }
          }
        },
        "responses": {
          "200": {
            "description": "Operation completed successfully. Note that the identifier, type, source, and relativePath properties will only be present if they were optionally passed in the request body.",
            "content": {
              "application/json": {
                "schema": {
                  "$ref": "#/components/schemas/duplicateOutput"
                }
              }
            }
          },
          "400": {
            "description": "Input is incorrect",
            "content": {
              "application/json": {
                "schema": {
                  "$ref": "#/components/schemas/ErrorOutputLCERROR400001"
                }
              }
            }
          },
          "401": {
            "description": "User is not authorized to access this service",
            "content": {
              "application/json": {
                "schema": {
                  "$ref": "#/components/schemas/ErrorOutputLCERROR401000"
                }
              }
            }
          },
          "403": {
            "description": "CSRF Token Not Validated",
            "content": {
              "application/json": {
                "schema": {
                  "$ref": "#/components/schemas/ErrorOutputLCERROR403000"
                }
              }
            }
          },
          "404": {
            "description": "Not Found",
            "content": {
              "application/json": {
                "schema": {
                  "$ref": "#/components/schemas/ErrorOutputLCERROR404000"
                }
              }
            }
          },
          "500": {
            "description": "Issue occured during request processing.",
            "content": {
              "application/json": {
                "schema": {
                  "$ref": "#/components/schemas/ErrorOutputLCERROR500002"
                }
              }
            }
          }
        }
      }
    },
    "/version/getGraph": {
      "post": {
        "summary": "Get the version graphs of objects",
        "description": "Get the version graphs for a list of objects. The request will be rejected if the total number of objects exceeds 50.",
        "operationId": "getGraph",
        "tags": [
          "Versioning"
        ],
        "parameters": [
          {
            "name": "SecurityContext",
            "in": "header",
            "description": "Security context the logged in user is using like ctx::RoleValue.OrganizationValue.CollaborativeSpaceValue",
            "required": true,
            "schema": {
              "type": "string"
            }
          },
          {
            "name": "ENO_CSRF_TOKEN",
            "in": "header",
            "description": "CSRF token could be obtained from dedicated web service /resources/v1/application/CSRF/",
            "required": true,
            "schema": {
              "type": "string"
            }
          }
        ],
        "requestBody": {
          "content": {
            "application/json": {
              "schema": {
                "$ref": "#/components/schemas/idListInputObjectReference"
              }
            }
          }
        },
        "responses": {
          "200": {
            "description": "Operation completed successfully. Note that the identifier, type, source, and relativePath properties will only be present if they were optionally passed in the request body.",
            "content": {
              "application/json": {
                "schema": {
                  "$ref": "#/components/schemas/getGraphOutput"
                }
              }
            }
          },
          "400": {
            "description": "Input is incorrect",
            "content": {
              "application/json": {
                "schema": {
                  "$ref": "#/components/schemas/ErrorOutputLCERROR400001"
                }
              }
            }
          },
          "401": {
            "description": "User is not authorized to access this service",
            "content": {
              "application/json": {
                "schema": {
                  "$ref": "#/components/schemas/ErrorOutputLCERROR401000"
                }
              }
            }
          },
          "403": {
            "description": "CSRF Token Not Validated",
            "content": {
              "application/json": {
                "schema": {
                  "$ref": "#/components/schemas/ErrorOutputLCERROR403000"
                }
              }
            }
          },
          "404": {
            "description": "Not Found",
            "content": {
              "application/json": {
                "schema": {
                  "$ref": "#/components/schemas/ErrorOutputLCERROR404000"
                }
              }
            }
          },
          "500": {
            "description": "Issue occured during request processing.",
            "content": {
              "application/json": {
                "schema": {
                  "$ref": "#/components/schemas/ErrorOutputLCERROR500002"
                }
              }
            }
          }
        }
      }
    }
  },
  "components": {
    "securitySchemes": {
      "BasicAuth": {
        "type": "http",
        "scheme": "basic"
      }
    },
    "schemas": {
      "idListInputObjectReference": {
        "required": [
          "data"
        ],
        "properties": {
          "data": {
            "type": "array",
            "items": {
              "type": "object",
              "required": [
                "id"
              ],
              "properties": {
                "id": {
                  "type": "string",
                  "example": "F718B05686760000926EEB5BE7400900"
                },
                "identifier": {
                  "type": "string",
                  "example": "F718B05686760000926EEB5BE7400900"
                },
                "type": {
                  "type": "string",
                  "example": "VPMReference"
                },
                "source": {
                  "type": "string",
                  "example": "$3DSpace"
                },
                "relativePath": {
                  "type": "string",
                  "example": "/resources/v1/modeler/dseng/dseng:EngItem/F718B05686760000926EEB5BE7400900"
                }
              }
            }
          }
        }
      },
      "idListInputObjectReferenceBranch": {
        "required": [
          "data"
        ],
        "properties": {
          "edgeType": {
            "description": "To revise : do not use or set to Revise (default).<br/>To branch : set to Branch.",
            "type": "string",
            "enum": [
              "Revision",
              "Branch"
            ],
            "example": "Branch"
          },
          "affix": {
            "description": "To revise : do not use or set to any value (not taken into account).<br/> To branch : do not use or set to desired value (taken into account).",
            "type": "string",
            "example": "br_"
          },
          "data": {
            "description": "revision and revisionComment are only allowed for types that allow it inside 3DDashboard",
            "type": "array",
            "items": {
              "type": "object",
              "required": [
                "id"
              ],
              "properties": {
                "id": {
                  "type": "string"
                },
                "identifier": {
                  "type": "string"
                },
                "type": {
                  "type": "string"
                },
                "source": {
                  "type": "string"
                },
                "relativePath": {
                  "type": "string"
                },
                "revision": {
                  "type": "string"
                },
                "revisionComment": {
                  "type": "string"
                }
              }
            }
          }
        },
        "example": {
          "edgeType": "branch",
          "affix": "br_",
          "data": [
            {
              "id": "F718B05686760000926EEB5BE7400900",
              "identifier": "F718B05686760000926EEB5BE7400900",
              "type": "VPMReference",
              "source": "$3DSpace",
              "relativePath": "/resources/v1/modeler/dseng/dseng:EngItem/F718B05686760000926EEB5BE7400900",
              "revisionComment": "My revision comment"
            }
          ]
        }
      },
      "idListInput": {
        "required": [
          "data"
        ],
        "properties": {
          "data": {
            "type": "array",
            "items": {
              "type": "object",
              "required": [
                "id"
              ],
              "properties": {
                "id": {
                  "type": "string",
                  "example": "F718B05686760000926EEB5BE7400900"
                }
              }
            }
          }
        }
      },
      "idListInputRef": {
        "required": [
          "data"
        ],
        "properties": {
          "data": {
            "type": "array",
            "items": {
              "type": "object",
              "required": [
                "id"
              ],
              "properties": {
                "id": {
                  "type": "string",
                  "example": "F718B05686760000926EEB5BE7400900"
                },
                "identifier": {
                  "type": "string",
                  "example": "F718B05686760000926EEB5BE7400900"
                },
                "type": {
                  "type": "string",
                  "example": "VPMReference"
                },
                "source": {
                  "type": "string",
                  "example": "$3DSpace"
                },
                "relativePath": {
                  "type": "string",
                  "example": "/resources/v1/modeler/dseng/dseng:EngItem/F718B05686760000926EEB5BE7400900"
                }
              }
            }
          }
        }
      },
      "getSharingInput": {
        "required": [
          "data"
        ],
        "properties": {
          "data": {
            "type": "array",
            "items": {
              "type": "object",
              "required": [
                "objectID"
              ],
              "properties": {
                "objectID": {
                  "type": "string",
                  "example": "A0FA2BBC511341228E0B5426C88C4E90"
                },
                "identifier": {
                  "type": "string",
                  "example": "A0FA2BBC511341228E0B5426C88C4E90"
                },
                "type": {
                  "type": "string",
                  "example": "VPMReference"
                },
                "source": {
                  "type": "string",
                  "example": "$3DSpace"
                },
                "relativePath": {
                  "type": "string",
                  "example": "/resources/v1/modeler/dseng/dseng:EngItem/A0FA2BBC511341228E0B5426C88C4E90"
                }
              }
            }
          }
        }
      },
      "getSharingOutput": {
        "properties": {
          "results": {
            "type": "array",
            "items": {
              "type": "object",
              "properties": {
                "objectID": {
                  "type": "string",
                  "example": "A0FA2BBC511341228E0B5426C88C4E90"
                },
                "sharings": {
                  "type": "object",
                  "properties": {
                    "users": {
                      "type": "array",
                      "items": {
                        "type": "object",
                        "properties": {
                          "userID": {
                            "type": "string",
                            "example": "user1"
                          },
                          "access": {
                            "type": "string",
                            "example": "Can Read"
                          }
                        }
                      }
                    },
                    "collabSpaces": {
                      "type": "array",
                      "items": {
                        "type": "object",
                        "properties": {
                          "collabSpaceID": {
                            "type": "string",
                            "example": "cs1"
                          },
                          "orgID": {
                            "type": "string",
                            "example": "MyCompany"
                          },
                          "access": {
                            "type": "string",
                            "example": "Can Edit"
                          }
                        }
                      }
                    },
                    "userGroups": {
                      "type": "array",
                      "items": {
                        "type": "object",
                        "properties": {
                          "userGroupID": {
                            "type": "string",
                            "example": "<uuid:04fdc808-5698-4c0d-a7bc-09a9232e0c5d>"
                          },
                          "access": {
                            "type": "string",
                            "example": "None"
                          }
                        }
                      }
                    }
                  }
                }
              }
            }
          }
        }
      },
      "setSharingInput": {
        "required": [
          "data"
        ],
        "properties": {
          "data": {
            "type": "array",
            "items": {
              "type": "object",
              "required": [
                "objectID",
                "sharings"
              ],
              "properties": {
                "objectID": {
                  "type": "string",
                  "example": "A0FA2BBC511341228E0B5426C88C4E90"
                },
                "identifier": {
                  "type": "string",
                  "example": "A0FA2BBC511341228E0B5426C88C4E90"
                },
                "type": {
                  "type": "string",
                  "example": "VPMReference"
                },
                "source": {
                  "type": "string",
                  "example": "$3DSpace"
                },
                "relativePath": {
                  "type": "string",
                  "example": "/resources/v1/modeler/dseng/dseng:EngItem/A0FA2BBC511341228E0B5426C88C4E90"
                },
                "sharings": {
                  "type": "object",
                  "required": [
                    "users",
                    "collabSpaces",
                    "userGroups"
                  ],
                  "properties": {
                    "users": {
                      "type": "array",
                      "items": {
                        "type": "object",
                        "required": [
                          "userID",
                          "access"
                        ],
                        "properties": {
                          "userID": {
                            "type": "string",
                            "example": "user1"
                          },
                          "access": {
                            "type": "string",
                            "example": "Can Read"
                          }
                        }
                      }
                    },
                    "collabSpaces": {
                      "type": "array",
                      "items": {
                        "type": "object",
                        "required": [
                          "collabSpaceID",
                          "orgID",
                          "access"
                        ],
                        "properties": {
                          "collabSpaceID": {
                            "type": "string",
                            "example": "cs1"
                          },
                          "orgID": {
                            "type": "string",
                            "example": "MyCompany"
                          },
                          "access": {
                            "type": "string",
                            "example": "Can Edit"
                          }
                        }
                      }
                    },
                    "userGroups": {
                      "type": "array",
                      "items": {
                        "type": "object",
                        "required": [
                          "userGroupID",
                          "access"
                        ],
                        "properties": {
                          "userGroupID": {
                            "type": "string",
                            "example": "<uuid:04fdc808-5698-4c0d-a7bc-09a9232e0c5d>"
                          },
                          "access": {
                            "type": "string",
                            "example": "None"
                          }
                        }
                      }
                    }
                  }
                }
              }
            }
          }
        }
      },
      "setSharingOutput": {
        "properties": {
          "errorCode": {
            "type": "string",
            "example": "0"
          },
          "errorMessage": {
            "type": "string",
            "example": "Success"
          }
        }
      },
      "transferListInput": {
        "required": [
          "data"
        ],
        "properties": {
          "owner": {
            "type": "string",
            "example": "user2"
          },
          "organization": {
            "type": "string",
            "example": "MyCompany"
          },
          "collabspace": {
            "type": "string",
            "example": "My Collaboration Space"
          },
          "data": {
            "type": "array",
            "items": {
              "type": "object",
              "required": [
                "id"
              ],
              "properties": {
                "id": {
                  "type": "string",
                  "example": "F718B05686760000926EEB5BE7400900"
                },
                "identifier": {
                  "type": "string",
                  "example": "F718B05686760000926EEB5BE7400900"
                },
                "type": {
                  "type": "string",
                  "example": "VPMReference"
                },
                "source": {
                  "type": "string",
                  "example": "$3DSpace"
                },
                "relativePath": {
                  "type": "string",
                  "example": "/resources/v1/modeler/dseng/dseng:EngItem/F718B05686760000926EEB5BE7400900"
                }
              }
            }
          }
        }
      },
      "changeStateListInput": {
        "required": [
          "data"
        ],
        "properties": {
          "data": {
            "type": "array",
            "items": {
              "type": "object",
              "required": [
                "id"
              ],
              "properties": {
                "id": {
                  "type": "string",
                  "example": "F718B05686760000926EEB5BE7400900"
                },
                "identifier": {
                  "type": "string",
                  "example": "F718B05686760000926EEB5BE7400900"
                },
                "type": {
                  "type": "string",
                  "example": "VPMReference"
                },
                "source": {
                  "type": "string",
                  "example": "$3DSpace"
                },
                "relativePath": {
                  "type": "string",
                  "example": "/resources/v1/modeler/dseng/dseng:EngItem/F718B05686760000926EEB5BE7400900"
                },
                "nextState": {
                  "type": "string",
                  "example": "FROZEN"
                }
              }
            }
          }
        }
      },
      "duplicateidListInput": {
        "required": [
          "data"
        ],
        "properties": {
          "affix": {
            "type": "string",
            "example": "CopyOf"
          },
          "data": {
            "type": "array",
            "items": {
              "type": "object",
              "required": [
                "id"
              ],
              "properties": {
                "id": {
                  "type": "string",
                  "example": "F718B05686760000926EEB5BE7400900"
                },
                "identifier": {
                  "type": "string",
                  "example": "F718B05686760000926EEB5BE7400900"
                },
                "type": {
                  "type": "string",
                  "example": "VPMReference"
                },
                "source": {
                  "type": "string",
                  "example": "$3DSpace"
                },
                "relativePath": {
                  "type": "string",
                  "example": "/resources/v1/modeler/dseng/dseng:EngItem/F718B05686760000926EEB5BE7400900"
                }
              }
            }
          }
        }
      },
      "getNextStatesOutput": {
        "properties": {
          "results": {
            "type": "array",
            "items": {
              "type": "object",
              "properties": {
                "id": {
                  "type": "string",
                  "example": "F718B05686760000926EEB5BE7400900",
                  "description": "The object identifier"
                },
                "nextStates": {
                  "description": "The next possible maturity states for the object",
                  "type": "array",
                  "items": {
                    "type": "string",
                    "example": "PRIVATE"
                  }
                },
                "maturityState": {
                  "type": "string",
                  "example": "IN_WORK",
                  "description": "The current maturity state of the object"
                },
                "policy": {
                  "type": "string",
                  "example": "VPLM_SMB_Definition",
                  "description": "The current policy"
                }
              }
            }
          }
        }
      },
      "changeStateOutput": {
        "properties": {
          "results": {
            "type": "array",
            "items": {
              "type": "object",
              "properties": {
                "id": {
                  "type": "string",
                  "example": "F718B05686760000926EEB5BE7400900",
                  "description": "The object identifier"
                },
                "maturityState": {
                  "description": "The resulting maturity state for the object",
                  "type": "string",
                  "example": "FROZEN"
                }
              }
            }
          }
        }
      },
      "reservationOutput": {
        "properties": {
          "results": {
            "type": "array",
            "items": {
              "type": "object",
              "properties": {
                "id": {
                  "type": "string",
                  "example": "F718B05686760000926EEB5BE7400900",
                  "description": "The object identifier"
                },
                "reserved": {
                  "description": "The reservation status of the object.",
                  "type": "boolean"
                },
                "reservedBy": {
                  "description": "The userid holding the reservation of the object.",
                  "type": "string"
                }
              }
            }
          }
        }
      },
      "transferOutput": {
        "properties": {
          "results": {
            "type": "array",
            "items": {
              "type": "object",
              "properties": {
                "owner": {
                  "type": "string",
                  "example": "user2",
                  "description": "The user id of the object transferred. "
                },
                "organization": {
                  "type": "string",
                  "example": "MyOrganization",
                  "description": "The organization id of the object transferred. "
                },
                "collabspace": {
                  "type": "string",
                  "example": "My Collaboration Space",
                  "description": "The collaboration space id of the object transferred. "
                },
                "id": {
                  "type": "string",
                  "example": "F718B05686760000926EEB5BE7400900",
                  "description": "The object identifier"
                },
                "Status": {
                  "description": "The status of the transfer on the object",
                  "type": "integer",
                  "example": 200
                }
              }
            }
          }
        }
      },
      "transferOutputPartialSuccess": {
        "example": [
          {
            "owner": "user2",
            "organization": "MyOrganization",
            "collabspace": "My Collaboration Space",
            "id": "F718B05686760000926EEB5BE7400900",
            "Status": 200
          },
          {
            "owner": "user2",
            "organization": "MyOrganization",
            "collabspace": "My Collaboration Space",
            "id": "F718B05686760000988EEB5BE7400900",
            "Status": 400,
            "ErrorReport": {
              "errorMessage": "Insufficient rights to transfer."
            }
          }
        ],
        "properties": {
          "results": {
            "type": "array",
            "items": {
              "type": "object",
              "properties": {
                "owner": {
                  "type": "string",
                  "example": "user2",
                  "description": "The user id of the object transferred. "
                },
                "organization": {
                  "type": "string",
                  "example": "MyOrganization",
                  "description": "The organization id of the object transferred. "
                },
                "collabspace": {
                  "type": "string",
                  "example": "My Collaboration Space",
                  "description": "The collaboration space id of the object transferred. "
                },
                "id": {
                  "type": "string",
                  "example": "F718B05686760000926EEB5BE7400900",
                  "description": "The object identifier"
                },
                "Status": {
                  "description": "The status of the transfer on the object",
                  "type": "integer",
                  "example": 400
                },
                "ErrorReport": {
                  "type": "object",
                  "properties": {
                    "errorMessage": {
                      "type": "string",
                      "example": "Insufficient rights to transfer",
                      "description": "Error message"
                    }
                  }
                }
              }
            }
          }
        }
      },
      "duplicateOutput": {
        "properties": {
          "results": {
            "type": "array",
            "items": {
              "type": "object",
              "properties": {
                "id": {
                  "type": "string",
                  "example": "F718B05686760000926EEB5BE7400900",
                  "description": "The identifier of the new object."
                },
                "identifier": {
                  "type": "string",
                  "example": "F718B05686760000926EEB5BE7400900",
                  "description": "The identifier of the new object."
                },
                "source": {
                  "type": "string",
                  "example": "$3DSpace",
                  "description": "The source of the new object."
                },
                "type": {
                  "type": "string",
                  "example": "VPMReference",
                  "description": "The type of the new object."
                },
                "relativePath": {
                  "type": "string",
                  "example": "/resources/v1/modeler/dseng/dseng:EngItem/F6AF82561E5700005EB123650003C100",
                  "description": "The relative path of the new object."
                },
                "derivedFrom": {
                  "type": "string",
                  "example": "F718B05686760000926EEB5BE7400900",
                  "description": "The identifier of the origin object."
                }
              }
            }
          }
        }
      },
      "ErrorOutput": {
        "properties": {
          "errorCode": {
            "type": "string",
            "example": "1"
          },
          "errorMessage": {
            "type": "string",
            "example": "Error Message"
          }
        }
      },
      "ErrorOutput400": {
        "properties": {
          "errorMessage": {
            "type": "string",
            "example": "Bad Request"
          }
        }
      },
      "ErrorOutputLCERROR400001": {
        "properties": {
          "errorCode": {
            "type": "string",
            "example": "LCERROR400001"
          },
          "errorMessage": {
            "type": "string",
            "example": "Bad Payload"
          }
        }
      },
      "ErrorOutputLCERROR403000": {
        "properties": {
          "errorCode": {
            "type": "string",
            "example": "LCERROR403000"
          },
          "errorMessage": {
            "type": "string",
            "example": "server message"
          }
        }
      },
      "ErrorOutputLCERROR401000": {
        "properties": {
          "errorCode": {
            "type": "string",
            "example": "LCERROR401000"
          },
          "errorMessage": {
            "type": "string",
            "example": "Missing or incorrect security context"
          }
        }
      },
      "ErrorOutputLCERROR500002": {
        "properties": {
          "errorCode": {
            "type": "string",
            "example": "LCERROR500002"
          },
          "errorMessage": {
            "type": "string",
            "example": "Version Failed: with server message"
          }
        }
      },
      "ErrorOutputDupLCERROR500002": {
        "properties": {
          "errorCode": {
            "type": "string",
            "example": "LCERROR500002"
          },
          "errorMessage": {
            "type": "string",
            "example": "Duplicate Failed: with server message"
          }
        }
      },
      "ErrorOutput401": {
        "properties": {
          "errorMessage": {
            "type": "string",
            "example": "Unauthorized Access"
          }
        }
      },
      "ErrorOutput500": {
        "properties": {
          "errorMessage": {
            "type": "string",
            "example": "Internal Server Error"
          }
        }
      },
      "ErrorOutputLCERROR404000": {
        "properties": {
          "errorCode": {
            "type": "string",
            "example": "LCERROR404000"
          },
          "errorMessage": {
            "type": "string",
            "example": "Not Found : Business object does not exist"
          }
        }
      },
      "getGraphOutput": {
        "example": [
          {
            "versions": [
              {
                "maturityState": "IN_WORK",
                "id": "5045B056C51000005EA6A93000166A76",
                "identifier": "5045B056C51000005EA6A93000166A76",
                "type": "VPMReference",
                "source": "$3DSpace",
                "relativePath": "/resources/v1/modeler/dseng/dseng:EngItem/5045B056C51000005EA6A93000166A76",
                "ancestors": [
                  {
                    "edgeType": "Revision",
                    "id": "F718B05686760000926EEB5BE7400900",
                    "identifier": "F718B05686760000926EEB5BE7400900",
                    "type": "VPMReference",
                    "source": "$3DSpace",
                    "relativePath": "/resources/v1/modeler/dseng/dseng:EngItem/F718B05686760000926EEB5BE7400900"
                  }
                ],
                "revision": "B.1"
              },
              {
                "maturityState": "IN_WORK",
                "id": "F718B05686760000926EEB5BE7400900",
                "identifier": "F718B05686760000926EEB5BE7400900",
                "type": "VPMReference",
                "source": "$3DSpace",
                "relativePath": "/resources/v1/modeler/dseng/dseng:EngItem/F718B05686760000926EEB5BE7400900",
                "revision": "A.1"
              }
            ],
            "id": "F718B05686760000926EEB5BE7400900",
            "identifier": "F718B05686760000926EEB5BE7400900",
            "type": "VPMReference",
            "source": "$3DSpace",
            "relativePath": "/resources/v1/modeler/dseng/dseng:EngItem/F718B05686760000926EEB5BE7400900"
          }
        ],
        "properties": {
          "results": {
            "type": "array",
            "items": {
              "type": "object",
              "properties": {
                "id": {
                  "type": "string",
                  "example": "F718B05686760000926EEB5BE7400900",
                  "description": "The identifier of the origin object"
                },
                "identifier": {
                  "type": "string",
                  "example": "F718B05686760000926EEB5BE7400900",
                  "description": "The identifier of the new object."
                },
                "source": {
                  "type": "string",
                  "example": "$3DSpace",
                  "description": "The source of the new object."
                },
                "type": {
                  "type": "string",
                  "example": "VPMReference",
                  "description": "The type of the new object."
                },
                "relativePath": {
                  "type": "string",
                  "example": "/resources/v1/modeler/dseng/dseng:EngItem/F718B05686760000926EEB5BE7400900",
                  "description": "The relative path of the new object."
                },
                "versions": {
                  "type": "array",
                  "items": {
                    "type": "object",
                    "properties": {
                      "id": {
                        "type": "string",
                        "example": "5045B056C51000005EA6A93000166A76",
                        "description": "The identifier of the version"
                      },
                      "identifier": {
                        "type": "string",
                        "example": "5045B056C51000005EA6A93000166A76",
                        "description": "The identifier of the new object."
                      },
                      "source": {
                        "type": "string",
                        "example": "$3DSpace",
                        "description": "The source of the new object."
                      },
                      "type": {
                        "type": "string",
                        "example": "VPMReference",
                        "description": "The type of the new object."
                      },
                      "relativePath": {
                        "type": "string",
                        "example": "/resources/v1/modeler/dseng/dseng:EngItem/5045B056C51000005EA6A93000166A76",
                        "description": "The relative path of the new object."
                      },
                      "maturityState": {
                        "type": "string",
                        "example": "IN_WORK",
                        "description": "The maturity state of the version."
                      },
                      "revision": {
                        "type": "string",
                        "example": "B.1",
                        "description": "Revision name"
                      },
                      "ancestors": {
                        "type": "array",
                        "items": {
                          "type": "object",
                          "properties": {
                            "edgeType": {
                              "type": "string",
                              "example": "Revision",
                              "description": "The operation used to create the version. May be Revision,Branch,RevisionFrom or MinorRevision"
                            },
                            "id": {
                              "type": "string",
                              "example": "F718B05686760000926EEB5BE7400900",
                              "description": "The identifier of the ancestor"
                            },
                            "identifier": {
                              "type": "string",
                              "example": "F718B05686760000926EEB5BE7400900",
                              "description": "The identifier of the new object."
                            },
                            "source": {
                              "type": "string",
                              "example": "$3DSpace",
                              "description": "The source of the new object."
                            },
                            "type": {
                              "type": "string",
                              "example": "VPMReference",
                              "description": "The type of the new object."
                            },
                            "relativePath": {
                              "type": "string",
                              "example": "/resources/v1/modeler/dseng/dseng:EngItem/F718B05686760000926EEB5BE7400900",
                              "description": "The relative path of the new object."
                            }
                          }
                        }
                      }
                    }
                  }
                }
              }
            }
          }
        }
      }
    }
  }
}